__init__.py
storkpubutils.py
starkware_helpers/math_utils.py
starkware_helpers/pedersen_params.json
starkware_helpers/signature.py
storkpubutils-0.4.3.dist-info/LICENSE
storkpubutils-0.4.3.dist-info/METADATA
storkpubutils-0.4.3.dist-info/WHEEL
storkpubutils-0.4.3.dist-info/top_level.txt
storkpubutils-0.4.3.dist-info/RECORD
