Metadata-Version: 2.1
Name: storkpubutils
Version: 0.4.3
Summary: Stork publisher utilities
Author-email: Yash Malik <ymalik@stork.network>
License: MIT License
Project-URL: Homepage, https://github.com/Stork-Oracle/storkpubutils
Project-URL: Bug Tracker, https://github.com/Stork-Oracle/storkpubutils/issues
Classifier: Programming Language :: Python :: 3
Classifier: License :: OSI Approved :: MIT License
Classifier: Operating System :: OS Independent
Requires-Python: >=3.9
License-File: LICENSE
